{
  "parent": "minecraft:recipes/root",
  "criteria": {
    "has_magma_shard": {
      "conditions": {
        "items": [
          {
            "items": [
              "oretastic:magma_shard"
            ]
          }
        ]
      },
      "trigger": "minecraft:inventory_changed"
    },
    "has_the_recipe": {
      "conditions": {
        "recipe": "minecraft:magma_ingot"
      },
      "trigger": "minecraft:recipe_unlocked"
    }
  },
  "requirements": [
    [
      "has_the_recipe",
      "has_magma_shard"
    ]
  ],
  "rewards": {
    "recipes": [
      "minecraft:magma_ingot"
    ]
  },
  "sends_telemetry_event": false
}